ILCDIRAC/__init__.py
ILCDIRAC/CalibrationSystem/ConfigTemplate.cfg
ILCDIRAC/CalibrationSystem/TODO
ILCDIRAC/CalibrationSystem/__init__.py
ILCDIRAC/CalibrationSystem/dev_create_events.py
ILCDIRAC/CalibrationSystem/Agent/CalibrationAgent.py
ILCDIRAC/CalibrationSystem/Agent/__init__.py
ILCDIRAC/CalibrationSystem/Client/CalibrationClient.py
ILCDIRAC/CalibrationSystem/Client/__init__.py
ILCDIRAC/CalibrationSystem/Service/CalibrationHandler.py
ILCDIRAC/CalibrationSystem/Service/CalibrationRun.py
ILCDIRAC/CalibrationSystem/Service/DetectorSettings.py
ILCDIRAC/CalibrationSystem/Service/__init__.py
ILCDIRAC/CalibrationSystem/Test/Test_CalibrationAgent.py
ILCDIRAC/CalibrationSystem/Test/Test_CalibrationClient.py
ILCDIRAC/CalibrationSystem/Test/Test_CalibrationService.py
ILCDIRAC/CalibrationSystem/Test/Test_Util_fileutils.py
ILCDIRAC/CalibrationSystem/Test/Test_Util_functions.py
ILCDIRAC/CalibrationSystem/Test/__init__.py
ILCDIRAC/CalibrationSystem/Utilities/__init__.py
ILCDIRAC/CalibrationSystem/Utilities/fileutils.py
ILCDIRAC/CalibrationSystem/Utilities/functions.py
ILCDIRAC/CalibrationSystem/Utilities/mergePandoraLikelihoodData.py
ILCDIRAC/CalibrationSystem/Utilities/objectFactory.py
ILCDIRAC/CalibrationSystem/Utilities/Python_Read_Scripts/ECal_Digi_Extract.py
ILCDIRAC/CalibrationSystem/Utilities/Python_Read_Scripts/EM_Extract.py
ILCDIRAC/CalibrationSystem/Utilities/Python_Read_Scripts/Extract_GeVToMIP.py
ILCDIRAC/CalibrationSystem/Utilities/Python_Read_Scripts/Extract_SimCaloHitMIPMPV.py
ILCDIRAC/CalibrationSystem/Utilities/Python_Read_Scripts/Final_Calibration.py
ILCDIRAC/CalibrationSystem/Utilities/Python_Read_Scripts/Final_Calibration.py.orig
ILCDIRAC/CalibrationSystem/Utilities/Python_Read_Scripts/HCal_Digi_Extract.py
ILCDIRAC/CalibrationSystem/Utilities/Python_Read_Scripts/HCal_Direction_Corrections_Extract.py
ILCDIRAC/CalibrationSystem/Utilities/Python_Read_Scripts/HCal_Ring_Digi_Extract.py
ilcdirac-35.0.8.dist-info/METADATA
ilcdirac-35.0.8.dist-info/WHEEL
ilcdirac-35.0.8.dist-info/entry_points.txt
ilcdirac-35.0.8.dist-info/top_level.txt
ilcdirac-35.0.8.dist-info/RECORD
